LICENCE
README.md
setup.py
Loterias/Apurar - Copia.py
Loterias/Apurar.py
Loterias/Collection.py
Loterias/Collections.py
Loterias/Conferir.py
Loterias/ConferirCollection.py
Loterias/Interpoler.py
Loterias/Loto.py
Loterias/__init__.py
Loterias.egg-info/PKG-INFO
Loterias.egg-info/SOURCES.txt
Loterias.egg-info/dependency_links.txt
Loterias.egg-info/requires.txt
Loterias.egg-info/top_level.txt