Metadata-Version: 2.1
Name: Loterias
Version: 0.0.11
Summary: Wrapper não oficial para pesquisa de dados lotéricos em thread
Home-page: UNKNOWN
Author: PKG
Author-email: drjpp.drjpp@gmail.com
License: MIT License
Keywords: loterias CEF
Platform: UNKNOWN
License-File: LICENCE
